{"id":"e8ee8814e1e37f756df4a870799970515fb0ad9f","axis":"silent","repo":"kermitt2/grobid","sha":"e8ee8814e1e37f756df4a870799970515fb0ad9f","parsed":{"files":[{"path":"grobid-core/src/main/java/org/grobid/core/engines/Engine.java","lines":["@@ -39,6 +39,7 @@"," import org.grobid.core.lang.Language;"," import org.grobid.core.utilities.Consolidation;"," import org.grobid.core.utilities.LanguageUtilities;","+import org.grobid.core.utilities.TextUtilities;"," import org.grobid.core.utilities.Utilities;"," import org.grobid.core.utilities.counters.CntManager;"," import org.grobid.core.utilities.counters.impl.CntManagerFactory;","@@ -548,11 +549,11 @@ public String processHeaderFunding(File inputFile, String md5Str, GrobidAnalysis","      * @param pathRaw      : the path where to put the sequence labeling feature file","      * @param pathTEI      : the path where to put the annotated TEI representation (the","      *                     file to be corrected for gold-level training data)","-     * @param id           : an optional ID to be used in the TEI file and the full text","-     *                     file, -1 if not used","+     * @param id           : unused, kept for backward compatibility; the xml:id is now","+     *                     derived from the input file name","      */","     public void createTrainingMonograph(File inputFile, String pathRaw, String pathTEI, int id) {","-        Document doc = parsers.getMonographParser().createTrainingFromPDF(inputFile, pathRaw, pathTEI, id);","+        parsers.getMonographParser().createTrainingFromPDF(inputFile, pathRaw, pathTEI);","     }"," ","     /**","@@ -563,11 +564,11 @@ public void createTrainingMonograph(File inputFile, String pathRaw, String pathT","      * @param pathRaw      : the path where to put the sequence labeling feature file","      * @param pathTEI      : the path where to put the annotated TEI representation (the","      *                     file to be annotated for \"from scratch\" training data)","-     * @param id           : an optional ID to be used in the TEI file and the full text","-     *                     file, -1 if not used","+     * @param id           : unused, kept for backward compatibility; the xml:id is now","+     *                     derived from the input file name","      */","     public void createTrainingBlank(File inputFile, String pathRaw, String pathTEI, int id) {","-        parsers.getSegmentationParser().createBlankTrainingData(inputFile, pathRaw, pathTEI, id);","+        parsers.getSegmentationParser().createBlankTrainingData(inputFile, pathRaw, pathTEI);","     }"," ","     /**","@@ -578,11 +579,12 @@ public void createTrainingBlank(File inputFile, String pathRaw, String pathTEI,","      * @param pathRaw      : the path where to put the sequence labeling feature file","      * @param pathTEI      : the path where to put the annotated TEI representation (the","      *                       file to be corrected for gold-level training data)","-     * @param id           : an optional ID to be used in the TEI file, -1 if not used","+     * @param id           : unused, kept for backward compatibility; the xml:id is now","+     *                       derived from the input file name","      */","     public void createTraining(File inputFile, String pathRaw, String pathTEI, int id, GrobidModels.Flavor flavor) {","         System.out.println(inputFile.getPath());","-        Document doc = parsers.getFullTextParser(flavor).createTraining(inputFile, pathRaw, pathTEI, id, flavor);","+        parsers.getFullTextParser(flavor).createTraining(inputFile, pathRaw, pathTEI, flavor);","     }"," ","     /**","@@ -691,8 +693,11 @@ public int batchCreateTraining(String directoryPath, String resultPath, int ind,","             // we process all pdf files in the directory","             File[] refFiles = path.listFiles(new FilenameFilter() {","                 public boolean accept(File dir, String name) {","-                    System.out.println(name);","-                    return name.endsWith(\".pdf\") || name.endsWith(\".PDF\");","+                    boolean isPdf = name.toLowerCase().endsWith(\".pdf\");","+                    if (isPdf) {","+                        System.out.println(name);","+                    }","+                    return isPdf;","                 }","             });"," ","@@ -745,8 +750,11 @@ public int batchCreateTrainingMonograph(String directoryPath, String resultPath,","             // we process all pdf files in the directory","             File[] refFiles = path.listFiles(new FilenameFilter() {","                 public boolean accept(File dir, String name) {","-                    System.out.println(name);","-                    return name.endsWith(\".pdf\") || name.endsWith(\".PDF\");","+                    boolean isPdf = name.toLowerCase().endsWith(\".pdf\");","+                    if (isPdf) {","+                        System.out.println(name);","+                    }","+                    return isPdf;","                 }","             });"," ","@@ -798,8 +806,11 @@ public int batchCreateTrainingBlank(String directoryPath, String resultPath, int","             // we process all pdf files in the directory","             File[] refFiles = path.listFiles(new FilenameFilter() {","                 public boolean accept(File dir, String name) {","-                    System.out.println(name);","-                    return name.endsWith(\".pdf\") || name.endsWith(\".PDF\");","+                    boolean isPdf = name.toLowerCase().endsWith(\".pdf\");","+                    if (isPdf) {","+                        System.out.println(name);","+                    }","+                    return isPdf;","                 }","             });"," ","@@ -1175,8 +1186,11 @@ public int batchCreateTrainingCitation(String directoryPath, String resultPath)","             // we process all pdf files in the directory","             File[] refFiles = path.listFiles(new FilenameFilter() {","                 public boolean accept(File dir, String name) {","-                    System.out.println(name);","-                    return name.endsWith(\".txt\");","+                    boolean isTxt = name.toLowerCase().endsWith(\".txt\");","+                    if (isTxt) {","+                        System.out.println(name);","+                    }","+                    return isTxt;","                 }","             });"," ","@@ -1185,7 +1199,6 @@ public boolean accept(File dir, String name) {"," ","             System.out.println(refFiles.length + \" files to be processed.\");"," ","-            int n = 0;","             for (final File txtFile : refFiles) {","                 try {","                     // read file line by line, assuming one reference string per line","@@ -1211,30 +1224,33 @@ public boolean accept(File dir, String name) {","                     if (bufferReference != null) {","                         bufferReference.append(\"\\n\");"," ","-                        Writer writerReference = new OutputStreamWriter(new FileOutputStream(new File(resultPath +","-                                File.separator +","-                                txtFile.getName().replace(\".txt\", \".training.references.tei.xml\")), false),","-                                StandardCharsets.UTF_8);","+                        // the sanitized base name is used for the training file name, while the xml:id","+                        // carries an additional leading '_' when required to be a valid NCName","+                        String baseName = TextUtilities.sanitizeFileName(","+                                txtFile.getName().replaceAll(\"(?i)\\\\.txt$\", \"\"));","+                        String xmlId = TextUtilities.sanitizeXmlId(baseName);","+","+                        File teiFile = new File(","+                                resultPath + File.separator + baseName + \".training.references.tei.xml\");","+                        try (Writer writerReference = new OutputStreamWriter(new FileOutputStream(teiFile, false),","+                                StandardCharsets.UTF_8)) {"," ","-                        writerReference.write(","-                                \"<?xml version=\\\"1.0\\\" ?>\\n<TEI xml:space=\\\"preserve\\\" xmlns=\\\"http://www.tei-c.org/ns/1.0\\\" \"","-                                        +","-                                        \"xmlns:xlink=\\\"http://www.w3.org/1999/xlink\\\" \"","-                                        +","-                                        \"\\n xmlns:mml=\\\"http://www.w3.org/1998/Math/MathML\\\">\\n\");","+                            writerReference.write(","+                                    \"<?xml version=\\\"1.0\\\" ?>\\n<TEI xml:space=\\\"preserve\\\" xmlns=\\\"http://www.tei-c.org/ns/1.0\\\" \"","+                                            + \"xmlns:xlink=\\\"http://www.w3.org/1999/xlink\\\" \"","+                                            + \"\\n xmlns:mml=\\\"http://www.w3.org/1998/Math/MathML\\\">\\n\");"," ","-                        writerReference.write(","-                                \"\\t<teiHeader>\\n\\t\\t<fileDesc xml:id=\\\"_\"","-                                        + n","-                                        +","-                                        \"\\\"/>\\n\\t</teiHeader>\\n\\t<text>\\n\\t\\t<front/>\\n\\t\\t<body/>\\n\\t\\t<back>\\n\");","+                            writerReference.write(","+                                    \"\\t<teiHeader>\\n\\t\\t<fileDesc xml:id=\\\"\"","+                                            + xmlId","+                                            + \"\\\"/>\\n\\t</teiHeader>\\n\\t<text>\\n\\t\\t<front/>\\n\\t\\t<body/>\\n\\t\\t<back>\\n\");"," ","-                        writerReference.write(\"<listBibl>\\n\");","+                            writerReference.write(\"<listBibl>\\n\");"," ","-                        writerReference.write(bufferReference.toString());","+                            writerReference.write(bufferReference.toString());"," ","-                        writerReference.write(\"\\t\\t</listBibl>\\n\\t</back>\\n\\t</text>\\n</TEI>\\n\");","-                        writerReference.close();","+                            writerReference.write(\"\\t\\t</listBibl>\\n\\t</back>\\n\\t</text>\\n</TEI>\\n\");","+                        }","                     }","                 } catch (final Exception exp) {","                     LOGGER.error(","@@ -1242,7 +1258,6 @@ public boolean accept(File dir, String name) {","                                     + txtFile.getPath(),","                             exp);","                 }","-                n++;","             }"," ","             return refFiles.length;"],"additions":52,"deletions":37,"truncated":false},{"path":"grobid-core/src/main/java/org/grobid/core/engines/FigureParser.java","lines":["@@ -261,8 +261,8 @@ public String getTEIHeader(String id) {","                 +","                 \"    <teiHeader>\\n\"","                 +","-                \"        <fileDesc xml:id=\\\"_\"","-                + id","+                \"        <fileDesc xml:id=\\\"\"","+                + TextUtilities.sanitizeXmlId(id)","                 + \"\\\"/>\\n\"","                 +","                 \"    </teiHeader>\\n\""],"additions":2,"deletions":2,"truncated":false},{"path":"grobid-core/src/main/java/org/grobid/core/engines/FullTextParser.java","lines":["@@ -1417,19 +1417,16 @@ private static int getDocIndexToken(Document doc, LayoutToken token) {","      * @param inputFile    input file","      * @param pathFullText path to fulltext","      * @param pathTEI      path to TEI","-     * @param id           id","      */","     public Document createTraining(File inputFile,","                                    String pathFullText,","-                                   String pathTEI,","-                                   int id) {","-        return createTraining(inputFile, pathFullText, pathTEI, id, null);","+                                   String pathTEI) {","+        return createTraining(inputFile, pathFullText, pathTEI, null);","     }"," ","     public Document createTraining(File inputFile,","                                    String pathFullText,","                                    String pathTEI,","-                                   int id,","                                    GrobidModels.Flavor flavor) {","         if (tmpPath == null)","             throw new GrobidResourceException(\"Cannot process pdf file, because temp path is null.\");","@@ -1443,7 +1440,12 @@ public Document createTraining(File inputFile,","                 throw new GrobidResourceException(\"Cannot train for fulltext, because file '\" +","                     inputFile.getAbsolutePath() + \"' does not exists.\");","             }","-            String pdfFileName = inputFile.getName();","+            // the sanitized base name is used for the training file names, while the xml:id values","+            // written in the generated TEI carry an additional leading '_' when the name starts","+            // with a character not allowed as first character of an NCName (e.g. a digit); the","+            // trainers map a TEI back to its raw feature files by stripping that leading '_'","+            String baseName = TextUtilities.sanitizeFileName(inputFile.getName().replaceAll(\"(?i)\\\\.pdf$\", \"\"));","+            String xmlId = TextUtilities.sanitizeXmlId(baseName);"," ","             // SEGMENTATION MODEL","             documentSource = DocumentSource.fromPdf(inputFile, -1, -1, false, true, true);","@@ -1461,10 +1463,10 @@ public Document createTraining(File inputFile,","             List<LayoutToken> tokenizations = doc.getTokenizations();"," ","             // we write first the full text untagged (but featurized with segmentation features)","-            String outPathFulltext = pathFullText + File.separator + pdfFileName.replaceAll(\"(?i)\\\\.pdf$\", \".training.segmentation\");","-            Writer writer = new OutputStreamWriter(new FileOutputStream(outPathFulltext, false), StandardCharsets.UTF_8);","-            writer.write(fulltext + \"\\n\");","-            writer.close();","+            String outPathFulltext = pathFullText + File.separator + baseName + \".training.segmentation\";","+            try (Writer writer = new OutputStreamWriter(new FileOutputStream(outPathFulltext, false), StandardCharsets.UTF_8)) {","+                writer.write(fulltext + \"\\n\");","+            }"," ","             // also write the raw text as seen before segmentation","             StringBuffer rawtxt = new StringBuffer();","@@ -1472,7 +1474,7 @@ public Document createTraining(File inputFile,","                 rawtxt.append(txtline.getText());","             }","             String outPathRawtext = pathFullText + File.separator +","-                pdfFileName.replaceAll(\"(?i)\\\\.pdf$\", \".training.segmentation.rawtxt\");","+                baseName + \".training.segmentation.rawtxt\";","             FileUtils.writeStringToFile(new File(outPathRawtext), rawtxt.toString(), StandardCharsets.UTF_8);"," ","             if (isNotBlank(fulltext)) {","@@ -1480,15 +1482,15 @@ public Document createTraining(File inputFile,","                 StringBuffer bufferFulltext = parsers.getSegmentationParser(flavor).trainingExtraction(rese, tokenizations, doc);"," ","                 // write the TEI file to reflect the exact layout of the text as extracted from the pdf","-                writer = new OutputStreamWriter(new FileOutputStream(new File(pathTEI +","+                try (Writer writer = new OutputStreamWriter(new FileOutputStream(new File(pathTEI +","                     File.separator +","-                    pdfFileName.replaceAll(\"(?i)\\\\.pdf$\", \".training.segmentation.tei.xml\")), false), StandardCharsets.UTF_8);","-                writer.write(\"<?xml version=\\\"1.0\\\" ?>\\n<tei xml:space=\\\"preserve\\\">\\n\\t<teiHeader>\\n\\t\\t<fileDesc xml:id=\\\"\" + id +","-                    \"\\\"/>\\n\\t</teiHeader>\\n\\t<text xml:lang=\\\"en\\\">\\n\");","+                    baseName + \".training.segmentation.tei.xml\"), false), StandardCharsets.UTF_8)) {","+                    writer.write(\"<?xml version=\\\"1.0\\\" ?>\\n<tei xml:space=\\\"preserve\\\">\\n\\t<teiHeader>\\n\\t\\t<fileDesc xml:id=\\\"\" + xmlId +","+                        \"\\\"/>\\n\\t</teiHeader>\\n\\t<text xml:lang=\\\"en\\\">\\n\");"," ","-                writer.write(bufferFulltext.toString());","-                writer.write(\"\\n\\t</text>\\n</tei>\\n\");","-                writer.close();","+                    writer.write(bufferFulltext.toString());","+                    writer.write(\"\\n\\t</text>\\n</tei>\\n\");","+                }","             }"," ","             doc = parsers.getSegmentationParser(flavor).processing(documentSource,","@@ -1499,30 +1501,29 @@ public Document createTraining(File inputFile,","             if (!referencesStr.isEmpty()) {","                 //String tei = parsers.getReferenceSegmenterParser().createTrainingData2(referencesStr, id);","                 Pair<String, String> result =","-                    parsers.getReferenceSegmenterParser().createTrainingData(doc, id);","+                    parsers.getReferenceSegmenterParser().createTrainingData(doc, baseName);","                 if (result != null) {","                     String tei = result.getLeft();","                     String raw = result.getRight();","                     if (tei != null) {","                         String outPath = pathTEI + \"/\" +","-                            pdfFileName.replaceAll(\"(?i)\\\\.pdf$\", \".training.references.referenceSegmenter.tei.xml\");","-                        writer = new OutputStreamWriter(new FileOutputStream(new File(outPath), false), StandardCharsets.UTF_8);","-                        writer.write(tei + \"\\n\");","-                        writer.close();","+                            baseName + \".training.references.referenceSegmenter.tei.xml\";","+                        try (Writer writer = new OutputStreamWriter(new FileOutputStream(new File(outPath), false), StandardCharsets.UTF_8)) {","+                            writer.write(tei + \"\\n\");","+                        }"," ","                         // generate also the raw vector file with the features","-                        outPath = pathTEI + \"/\" + pdfFileName.replaceAll(\"(?i)\\\\.pdf$\", \".training.references.referenceSegmenter\");","-                        writer = new OutputStreamWriter(new FileOutputStream(new File(outPath), false), StandardCharsets.UTF_8);","-                        writer.write(raw + \"\\n\");","-                        writer.close();","+                        outPath = pathTEI + \"/\" + baseName + \".training.references.referenceSegmenter\";","+                        try (Writer writer = new OutputStreamWriter(new FileOutputStream(new File(outPath), false), StandardCharsets.UTF_8)) {","+                            writer.write(raw + \"\\n\");","+                        }"," ","                         // also write the raw text as it is before reference segmentation","-                        outPathRawtext = pathTEI + \"/\" + pdfFileName","-                            .replace(\".pdf\", \".training.references.referenceSegmenter.rawtxt\");","-                        Writer strWriter = new OutputStreamWriter(","-                            new FileOutputStream(new File(outPathRawtext), false), StandardCharsets.UTF_8);","-                        strWriter.write(referencesStr + \"\\n\");","-                        strWriter.close();","+                        outPathRawtext = pathTEI + \"/\" + baseName + \".training.references.referenceSegmenter.rawtxt\";","+                        try (Writer strWriter = new OutputStreamWriter(","+                            new FileOutputStream(new File(outPathRawtext), false), StandardCharsets.UTF_8)) {","+                            strWriter.write(referencesStr + \"\\n\");","+                        }","                     }","                 }","             }","@@ -1551,60 +1552,56 @@ public Document createTraining(File inputFile,","                 if (bufferReference != null) {","                     bufferReference.append(\"\\n\");"," ","-                    Writer writerReference = new OutputStreamWriter(new FileOutputStream(new File(pathTEI +","+                    try (Writer writerReference = new OutputStreamWriter(new FileOutputStream(new File(pathTEI +","                         File.separator +","-                        pdfFileName.replaceAll(\"(?i)\\\\.pdf$\", \".training.references.tei.xml\")), false), StandardCharsets.UTF_8);","+                        baseName + \".training.references.tei.xml\"), false), StandardCharsets.UTF_8)) {"," ","-                    writerReference.write(\"<?xml version=\\\"1.0\\\" ?>\\n<TEI xml:space=\\\"preserve\\\" xmlns=\\\"http://www.tei-c.org/ns/1.0\\\" \" +","-                        \"xmlns:xlink=\\\"http://www.w3.org/1999/xlink\\\" \" +","-                        \"\\n xmlns:mml=\\\"http://www.w3.org/1998/Math/MathML\\\">\\n\");","-                    if (id == -1) {","-                        writerReference.write(\"\\t<teiHeader/>\\n\\t<text>\\n\\t\\t<front/>\\n\\t\\t<body/>\\n\\t\\t<back>\\n\");","-                    } else {","-                        writerReference.write(\"\\t<teiHeader>\\n\\t\\t<fileDesc xml:id=\\\"\" + id +","+                        writerReference.write(\"<?xml version=\\\"1.0\\\" ?>\\n<TEI xml:space=\\\"preserve\\\" xmlns=\\\"http://www.tei-c.org/ns/1.0\\\" \" +","+                            \"xmlns:xlink=\\\"http://www.w3.org/1999/xlink\\\" \" +","+                            \"\\n xmlns:mml=\\\"http://www.w3.org/1998/Math/MathML\\\">\\n\");","+                        writerReference.write(\"\\t<teiHeader>\\n\\t\\t<fileDesc xml:id=\\\"\" + xmlId +","                             \"\\\"/>\\n\\t</teiHeader>\\n\\t<text>\\n\\t\\t<front/>\\n\\t\\t<body/>\\n\\t\\t<back>\\n\");","-                    }","-                    writerReference.write(\"<listBibl>\\n\");","+                        writerReference.write(\"<listBibl>\\n\");"," ","-                    writerReference.write(bufferReference.toString());","+                        writerReference.write(bufferReference.toString());"," ","-                    writerReference.write(\"\\t\\t</listBibl>\\n\\t</back>\\n\\t</text>\\n</TEI>\\n\");","-                    writerReference.close();","+                        writerReference.write(\"\\t\\t</listBibl>\\n\\t</back>\\n\\t</text>\\n</TEI>\\n\");","+                    }"," ","                     // BIBLIO REFERENCE AUTHOR NAMES","-                    Writer writerName = new OutputStreamWriter(new FileOutputStream(new File(pathTEI +","+                    try (Writer writerName = new OutputStreamWriter(new FileOutputStream(new File(pathTEI +","                         File.separator +","-                        pdfFileName.replaceAll(\"(?i)\\\\.pdf$\", \".training.references.authors.tei.xml\")), false), StandardCharsets.UTF_8);","-","-                    writerName.write(\"<?xml version=\\\"1.0\\\" ?>\\n<TEI xml:space=\\\"preserve\\\" xmlns=\\\"http://www.tei-c.org/ns/1.0\\\" \" +","-                        \"xmlns:xlink=\\\"http://www.w3.org/1999/xlink\\\" \" +","-                        \"\\n xmlns:mml=\\\"http://www.w3.org/1998/Math/MathML\\\">\\n\");","-                    writerName.write(\"\\t<teiHeader>\\n\\t\\t<fileDesc>\\n\\t\\t\\t<sourceDesc>\\n\" +","-                        \"\\t\\t\\t\\t<biblStruct>\\n\\t\\t\\t\\t\\t<analytic>\\n\\n\");","-","-                    for (LabeledReferenceResult ref : references) {","-                        if (StringUtils.isNotBlank(ref.getReferenceText())) {","-                            BiblioItem bib = parsers.getCitationParser().processingString(ref.getReferenceText(), 0);","-                            if (bib != null) {","-                                String authorSequence = bib.getAuthors();","-                                if (StringUtils.isNotBlank(authorSequence)) {","-                                    /*List<String> inputs = new ArrayList<String>();","-                                    inputs.add(authorSequence);*/","-                                    StringBuilder bufferName = parsers.getAuthorParser().trainingExtraction(authorSequence, false);","-                                    if ((bufferName != null) && (bufferName.length() > 0)) {","-                                        writerName.write(\"\\n\\t\\t\\t\\t\\t\\t<author>\");","-                                        writerName.write(bufferName.toString());","-                                        writerName.write(\"</author>\\n\");","+                        baseName + \".training.references.authors.tei.xml\"), false), StandardCharsets.UTF_8)) {","+","+                        writerName.write(\"<?xml version=\\\"1.0\\\" ?>\\n<TEI xml:space=\\\"preserve\\\" xmlns=\\\"http://www.tei-c.org/ns/1.0\\\" \" +","+                            \"xmlns:xlink=\\\"http://www.w3.org/1999/xlink\\\" \" +","+                            \"\\n xmlns:mml=\\\"http://www.w3.org/1998/Math/MathML\\\">\\n\");","+                        writerName.write(\"\\t<teiHeader>\\n\\t\\t<fileDesc>\\n\\t\\t\\t<sourceDesc>\\n\" +","+                            \"\\t\\t\\t\\t<biblStruct>\\n\\t\\t\\t\\t\\t<analytic>\\n\\n\");","+","+                        for (LabeledReferenceResult ref : references) {","+                            if (StringUtils.isNotBlank(ref.getReferenceText())) {","+                                BiblioItem bib = parsers.getCitationParser().processingString(ref.getReferenceText(), 0);","+                                if (bib != null) {","+                                    String authorSequence = bib.getAuthors();","+                                    if (StringUtils.isNotBlank(authorSequence)) {","+                                        /*List<String> inputs = new ArrayList<String>();","+                                        inputs.add(authorSequence);*/","+                                        StringBuilder bufferName = parsers.getAuthorParser().trainingExtraction(authorSequence, false);","+                                        if ((bufferName != null) && (bufferName.length() > 0)) {","+                                            writerName.write(\"\\n\\t\\t\\t\\t\\t\\t<author>\");","+                                            writerName.write(bufferName.toString());","+                                            writerName.write(\"</author>\\n\");","+                                        }","                                     }","                                 }","                             }","                         }","-                    }"," ","-                    writerName.write(\"\\n\\t\\t\\t\\t\\t</analytic>\");","-                    writerName.write(\"\\n\\t\\t\\t\\t</biblStruct>\\n\\t\\t\\t</sourceDesc>\\n\\t\\t</fileDesc>\");","-                    writerName.write(\"\\n\\t</teiHeader>\\n</TEI>\\n\");","-                    writerName.close();","+                        writerName.write(\"\\n\\t\\t\\t\\t\\t</analytic>\");","+                        writerName.write(\"\\n\\t\\t\\t\\t</biblStruct>\\n\\t\\t\\t</sourceDesc>\\n\\t\\t</fileDesc>\");","+                        writerName.write(\"\\n\\t</teiHeader>\\n</TEI>\\n\");","+                    }","                 }","             }"," ","@@ -1621,10 +1618,10 @@ public Document createTraining(File inputFile,"," ","                     // we write the full text untagged","                     outPathFulltext = pathFullText + File.separator","-                        + pdfFileName.replaceAll(\"(?i)\\\\.pdf$\", \".training.fulltext\");","-                    writer = new OutputStreamWriter(new FileOutputStream(new File(outPathFulltext), false), StandardCharsets.UTF_8);","-                    writer.write(bodytext + \"\\n\");","-                    writer.close();","+                        + baseName + \".training.fulltext\";","+                    try (Writer writer = new OutputStreamWriter(new FileOutputStream(new File(outPathFulltext), false), StandardCharsets.UTF_8)) {","+                        writer.write(bodytext + \"\\n\");","+                    }"," ","                     //              StringTokenizer st = new StringTokenizer(fulltext, \"\\n\");","                     String rese = label(bodytext);","@@ -1632,49 +1629,45 @@ public Document createTraining(File inputFile,","                     StringBuilder bufferFulltext = trainingExtraction(rese, tokenizationsBody);"," ","                     // write the TEI file to reflect the extract layout of the text as extracted from the pdf","-                    writer = new OutputStreamWriter(new FileOutputStream(new File(pathTEI +","+                    try (Writer writer = new OutputStreamWriter(new FileOutputStream(new File(pathTEI +","                         File.separator +","-                        pdfFileName.replaceAll(\"(?i)\\\\.pdf$\", \".training.fulltext.tei.xml\")), false), StandardCharsets.UTF_8);","-                    if (id == -1) {","-                        writer.write(\"<?xml version=\\\"1.0\\\" ?>\\n<tei xml:space=\\\"preserve\\\">\\n\\t<teiHeader/>\\n\\t<text xml:lang=\\\"en\\\">\\n\");","-                    } else {","-                        writer.write(\"<?xml version=\\\"1.0\\\" ?>\\n<tei xml:space=\\\"preserve\\\">\\n\\t<teiHeader>\\n\\t\\t<fileDesc xml:id=\\\"\" + id +","+                        baseName + \".training.fulltext.tei.xml\"), false), StandardCharsets.UTF_8)) {","+                        writer.write(\"<?xml version=\\\"1.0\\\" ?>\\n<tei xml:space=\\\"preserve\\\">\\n\\t<teiHeader>\\n\\t\\t<fileDesc xml:id=\\\"\" + xmlId +","                             \"\\\"/>\\n\\t</teiHeader>\\n\\t<text xml:lang=\\\"en\\\">\\n\");","+                        writer.write(bufferFulltext.toString());","+                        writer.write(\"\\n\\t</text>\\n</tei>\\n\");","                     }","-                    writer.write(bufferFulltext.toString());","-                    writer.write(\"\\n\\t</text>\\n</tei>\\n\");","-                    writer.close();"," ","                     // training data for FIGURES","-                    Pair<String, String> trainingFigure = processTrainingDataFigures(rese, tokenizationsBody, inputFile.getName());","+                    Pair<String, String> trainingFigure = processTrainingDataFigures(rese, tokenizationsBody, baseName);","                     if (trainingFigure.getLeft().trim().length() > 0) {","                         String outPathFigures = pathFullText + File.separator","-                            + pdfFileName.replaceAll(\"(?i)\\\\.pdf$\", \".training.figure\");","-                        writer = new OutputStreamWriter(new FileOutputStream(new File(outPathFigures), false), StandardCharsets.UTF_8);","-                        writer.write(trainingFigure.getRight() + \"\\n\\n\");","-                        writer.close();","+                            + baseName + \".training.figure\";","+                        try (Writer writer = new OutputStreamWriter(new FileOutputStream(new File(outPathFigures), false), StandardCharsets.UTF_8)) {","+                            writer.write(trainingFigure.getRight() + \"\\n\\n\");","+                        }"," ","                         String outPathFiguresTEI = pathTEI + File.separator","-                            + pdfFileName.replaceAll(\"(?i)\\\\.pdf$\", \".training.figure.tei.xml\");","-                        writer = new OutputStreamWriter(new FileOutputStream(new File(outPathFiguresTEI), false), StandardCharsets.UTF_8);"],"additions":85,"deletions":94,"truncated":false}],"additions":139,"deletions":133,"truncated":true,"file_count":3},"error":null,"fetched_at":"2026-07-17T09:47:40.133235+00:00"}