{"id":"e72b482b6f975172c8eef813261c61ba061fc3fe","axis":"silent","repo":"pnpm/pnpm","package":{"name":"monorepo-root","ecosystem":"npm","version":"3.3.1","source":"package.json","version_count":32},"downloads":{"weekly":6024,"monthly":24096,"source":"npmjs.org","timeline_12w":[5292,4105,4617,4693,5118,5940,4512,4848,5424,4537,4426,0],"timeline_labels":["2026-04-22","2026-04-29","2026-05-06","2026-05-13","2026-05-20","2026-05-27","2026-06-03","2026-06-10","2026-06-17","2026-06-24","2026-07-01","2026-07-08"]},"dependents":{"direct":0,"indirect":0,"total":0,"source":"deps.dev_miss"},"blast_radius":{"score":3,"tier":"LOW","factors":["downloads:low"]},"enriched_at":"2026-07-08T09:56:26.892557+00:00"}